ASRscsvmv/__init__.py
ASRscsvmv/asrhscsvmv.py
ASRscsvmv/asrscsvmv.py
ASRscsvmv-1.1.3.dist-info/METADATA
ASRscsvmv-1.1.3.dist-info/WHEEL
ASRscsvmv-1.1.3.dist-info/licence.txt
ASRscsvmv-1.1.3.dist-info/top_level.txt
ASRscsvmv-1.1.3.dist-info/RECORD
