Metadata-Version: 2.1
Name: ASRscsvmv
Version: 1.1.3
Summary: This package recognizes and translates your words
Author: SCSVMV 22-23 PROJECT 17
License-File: licence.txt
Requires-Dist: vosk
Requires-Dist: PySimpleGUI
Requires-Dist: argostranslate
Requires-Dist: streamlit
Requires-Dist: pyaudio
